skq/__init__.py
skq/base.py
skq/constants.py
skq/utils.py
skq/circuits/__init__.py
skq/circuits/circuit.py
skq/circuits/deutsch.py
skq/circuits/entangled_states.py
skq/circuits/grover.py
skq/gates/__init__.py
skq/gates/base.py
skq/gates/global_phase.py
skq/gates/qubit/__init__.py
skq/gates/qubit/base.py
skq/gates/qubit/multi.py
skq/gates/qubit/single.py
skq/gates/qupent/__init__.py
skq/gates/qupent/base.py
skq/gates/qupent/single.py
skq/gates/ququart/__init__.py
skq/gates/ququart/base.py
skq/gates/ququart/single.py
skq/gates/qutrit/__init__.py
skq/gates/qutrit/base.py
skq/gates/qutrit/multi.py
skq/gates/qutrit/single.py
skq/quantum_info/__init__.py
skq/quantum_info/channel.py
skq/quantum_info/density.py
skq/quantum_info/hadamard.py
skq/quantum_info/hamiltonian.py
skq/quantum_info/state.py
skq/quantum_info/superoperator.py
skq-0.4.6.dist-info/LICENSE
skq-0.4.6.dist-info/METADATA
skq-0.4.6.dist-info/WHEEL
skq-0.4.6.dist-info/top_level.txt
skq-0.4.6.dist-info/RECORD
