Metadata-Version: 2.2
Name: skq
Version: 0.4.6
Summary: Scientific Toolkit for Quantum Computing
Author-email: Carlo Lepelaars <info@carlolepelaars.nl>
Requires-Python: <4,>=3.10
License-File: LICENSE
Requires-Dist: numpy<=2.0.2
Requires-Dist: plotly>=5.22.0
Requires-Dist: nbformat>=5.10.4
Requires-Dist: qiskit>=1.2.0
Requires-Dist: matplotlib>=3.9.1
Requires-Dist: pylatexenc>=2.10
Requires-Dist: scipy>=1.14.0
Requires-Dist: pennylane>=0.37.0
Provides-Extra: dev
Requires-Dist: pytest>=8.3.4; extra == "dev"
Requires-Dist: ruff>=0.8.4; extra == "dev"
